experiments/inheritance/__init__.py
experiments/inheritance/inheritance_experiments.py
experiments/tsp/__init__.py
experiments/tsp/tsp_experiments.py
optimizn/__init__.py
optimizn/lagrange_examples.py
optimizn/utils.py
optimizn/ab_split/opt_split.py
optimizn/ab_split/opt_split2.py
optimizn/ab_split/opt_split_dp.py
optimizn/ab_split/testing/cluster_hw.py
optimizn/ab_split/testing/test_opt_cases.py
optimizn/combinatorial/__init__.py
optimizn/combinatorial/branch_and_bound.py
optimizn/combinatorial/opt_problem.py
optimizn/combinatorial/simulated_annealing.py
optimizn/combinatorial/algorithms/__init__.py
optimizn/combinatorial/algorithms/binpacking/__init__.py
optimizn/combinatorial/algorithms/binpacking/bnb_binpacking.py
optimizn/combinatorial/algorithms/knapsack/__init__.py
optimizn/combinatorial/algorithms/knapsack/bnb_knapsack.py
optimizn/combinatorial/algorithms/min_path_cover/__init__.py
optimizn/combinatorial/algorithms/min_path_cover/bnb_min_path_cover.py
optimizn/combinatorial/algorithms/min_path_cover/sim_anneal_min_path_cover.py
optimizn/combinatorial/algorithms/suitcase_reshuffle/__init__.py
optimizn/combinatorial/algorithms/suitcase_reshuffle/bnb_suitcasereshuffle.py
optimizn/combinatorial/algorithms/suitcase_reshuffle/sim_anneal_suitcase_reshuffle.py
optimizn/combinatorial/algorithms/suitcase_reshuffle/suitcases.py
optimizn/combinatorial/algorithms/traveling_salesman/__init__.py
optimizn/combinatorial/algorithms/traveling_salesman/bnb_tsp.py
optimizn/combinatorial/algorithms/traveling_salesman/city_graph.py
optimizn/combinatorial/algorithms/traveling_salesman/sim_anneal_tsp.py
optimizn/continuous_training/__init__.py
optimizn/continuous_training/continuous_training.py
optimizn/problems/__init__.py
optimizn/problems/binary_assignment.py
optimizn/problems/int_allocn.py
optimizn/problems/sample_ci.py
optimizn/reinforcement_learning/__init__.py
optimizn/reinforcement_learning/multi_armed_bandit.py
optimizn/trees/pprnt.py
tests/combinatorial/__init__.py
optimizn-0.0.24.dist-info/LICENSE
optimizn-0.0.24.dist-info/METADATA
optimizn-0.0.24.dist-info/NOTICE.md
optimizn-0.0.24.dist-info/WHEEL
optimizn-0.0.24.dist-info/top_level.txt
optimizn-0.0.24.dist-info/RECORD
