Metadata-Version: 2.1
Name: optimizn
Version: 0.0.24
Summary: A Python library for developing customized optimization algorithms under general paradigms.
Author: Rohit Pandey, Akshay Sathiya
Author-email: rohitpandey576@gmail.com, akshay.sathiya@gmail.com
Requires-Python: >=2.7, !=3.0.*, !=3.1.*, !=3.2.*, !=3.3.*, <4
License-File: LICENSE
License-File: NOTICE.md
Requires-Dist: numpy
Requires-Dist: scipy
Requires-Dist: cvxpy
Provides-Extra: dev
Provides-Extra: test
Requires-Dist: pytest ; extra == 'test'
